helloworld.py
mohit96_helloworld-1.2.dist-info/LICENSE.txt
mohit96_helloworld-1.2.dist-info/METADATA
mohit96_helloworld-1.2.dist-info/WHEEL
mohit96_helloworld-1.2.dist-info/top_level.txt
mohit96_helloworld-1.2.dist-info/RECORD
