Metadata-Version: 2.1
Name: mohit96-helloworld
Version: 1.2
Summary: Say Hello!
Home-page: https://github.com/MohitChattlani/first-python-package-mohit
Author: Mohit Chattlani
License: UNKNOWN
Platform: UNKNOWN
Classifier: License :: OSI Approved :: MIT License
Classifier: Operating System :: OS Independent
Classifier: Programming Language :: Python :: 3
Classifier: Programming Language :: Python :: 3.6
Classifier: Programming Language :: Python :: 3.7
Requires-Dist: blessings (~=1.7)
Provides-Extra: dev
Requires-Dist: pytest (>=3.7) ; extra == 'dev'
